douyin_image/__init__.py
douyin_image/converter.py
douyin_image-0.1.dist-info/METADATA
douyin_image-0.1.dist-info/RECORD
douyin_image-0.1.dist-info/WHEEL
douyin_image-0.1.dist-info/entry_points.txt
douyin_image-0.1.dist-info/top_level.txt
