Metadata-Version: 2.1
Name: douyin-image
Version: 0.1
Summary: add douyin effect to image
Home-page: https://github.com/pythonml/douyin_image
Author: Zhongqiang Shen
Author-email: shenzhongqiang@msn.com
License: UNKNOWN
Platform: UNKNOWN
Classifier: Programming Language :: Python :: 3
Classifier: License :: OSI Approved :: MIT License
Classifier: Operating System :: OS Independent
Requires-Dist: Pillow (>=5.1.0)
Requires-Dist: numpy (==1.14.4)
